Workbook

Sheet Read me
A1: Event + partnerships ops kit · sample
A2: Made by Durva Thakkar for Clio's Strategic Engagement team · durvathakkar.com/clio
A4: What this is | B4: A ready-to-use ops workbook for one flagship event and the partner program around it. Works in Excel and Google Sheets.
A5: Sample data | B5: Every vendor, amount, name and date here is sample data I created to show the system. Nothing is Clio data.
A6: Event date | B6: Change 'Logistics'!C3 and every due date and 'days left' recalculates.
A7: Colour key | B7: Light blue cells are inputs. Everything else is a formula.
A8: Tabs | B8: Logistics · Vendors · Budget + reconciliation · Travel · Shipping · Volunteers · Comms calendar · Partner onboarding · Status + risks · AI workflow log

Sheet Logistics
A1: Logistics tracker · flagship conference (sample)
A2: Due date = event date minus days before. Days left updates every time you open the file.
B3: Event date | C3: 46321
A5: # | B5: Workstream | C5: Task | D5: Owner | E5: Days before event | F5: Due date | G5: Days left | H5: Status | I5: Notes
A6: 1 | B6: Vendors | C6: Onboard AV vendor (tax form, banking, insurance certificate) | D6: Coordinator | E6: 45 | F6: =$C$3-E6 | G6: =F6-TODAY() | H6: Done
A7: 2 | B7: Vendors | C7: Create PO for AV and staging | D7: Coordinator | E7: 40 | F7: =$C$3-E7 | G7: =F7-TODAY() | H7: Done | I7: PO approved
A8: 3 | B8: Contracts | C8: Contract signed with catering for partner dinner | D8: Program manager | E8: 35 | F8: =$C$3-E8 | G8: =F8-TODAY() | H8: Done
A9: 4 | B9: Swag | C9: Order swag: notebooks, pens, stickers (quantity = registrations x 1.1) | D9: Coordinator | E9: 30 | F9: =$C$3-E9 | G9: =F9-TODAY() | H9: Done
A10: 5 | B10: Shipping | C10: Ship booth kit to venue advance warehouse | D10: Coordinator | E10: 14 | F10: =$C$3-E10 | G10: =F10-TODAY() | H10: In progress | I10: Check the venue's receiving window
A11: 6 | B11: Travel | C11: Book team flights and hotel block | D11: Coordinator | E11: 21 | F11: =$C$3-E11 | G11: =F11-TODAY() | H11: Done
A12: 7 | B12: Speakers | C12: Collect final speaker slides and bios | D12: Program manager | E12: 10 | F12: =$C$3-E12 | G12: =F12-TODAY() | H12: In progress | I12: 8 of 40 outstanding
A13: 8 | B13: Sponsors | C13: Confirm sponsor booth assets and logo files | D13: Partnerships | E13: 10 | F13: =$C$3-E13 | G13: =F13-TODAY() | H13: Waiting | I13: 2 sponsors pending
A14: 9 | B14: Volunteers | C14: Volunteer roster final + briefing deck sent | D14: Coordinator | E14: 7 | F14: =$C$3-E14 | G14: =F14-TODAY() | H14: Not started
A15: 10 | B15: Payments | C15: Process deposits and local vendor payments | D15: Coordinator | E15: 7 | F15: =$C$3-E15 | G15: =F15-TODAY() | H15: In progress
A16: 11 | B16: Onsite | C16: Print signage and badge stock | D16: Coordinator | E16: 5 | F16: =$C$3-E16 | G16: =F16-TODAY() | H16: Not started
A17: 12 | B17: Wrap-up | C17: Expense reconciliation and post-event report | D17: Coordinator | E17: -7 | F17: =$C$3-E17 | G17: =F17-TODAY() | H17: Not started | I17: Due 7 days after
B19: Progress | C19: =COUNTIF(H6:H17,"Done")&" of "&COUNTA(H6:H17)&" done"

Sheet Vendors
A1: New vendor onboarding
A2: Nothing gets a PO until every column is Yes.
A4: Vendor | B4: Service | C4: Tax form | D4: Banking info | E4: Insurance cert | F4: Contract | G4: PO # | H4: Ready to pay?
A5: Northside AV | B5: Audio visual | C5: Yes | D5: Yes | E5: Yes | F5: Yes | G5: PO-2611 | H5: =IF(AND(C5="Yes",D5="Yes",E5="Yes",F5="Yes",G5<>""),"Yes","Not yet")
A6: Harbour Catering | B6: Partner dinner | C6: Yes | D6: Yes | E6: No | F6: Yes | G6: PO-2614 | H6: =IF(AND(C6="Yes",D6="Yes",E6="Yes",F6="Yes",G6<>""),"Yes","Not yet")
A7: Print Lab | B7: Signage + badges | C7: Yes | D7: No | E7: Yes | F7: No | H7: =IF(AND(C7="Yes",D7="Yes",E7="Yes",F7="Yes",G7<>""),"Yes","Not yet")
A8: Swag Supply Co. | B8: Branded swag | C8: Yes | D8: Yes | E8: Yes | F8: Yes | G8: PO-2602 | H8: =IF(AND(C8="Yes",D8="Yes",E8="Yes",F8="Yes",G8<>""),"Yes","Not yet")

Sheet Budget + reconciliation
A1: Budget and expense reconciliation (sample figures, USD)
A2: Variance over 5% or a missing receipt gets flagged before month-end close.
A4: Line | B4: Vendor | C4: Budget | D4: PO amount | E4: Invoiced | F4: Paid | G4: Receipt on file? | H4: Variance vs budget | I4: Flag
A5: Audio visual | B5: Northside AV | C5: 18000 | D5: 18000 | E5: 18450 | F5: 18450 | G5: Yes | H5: =IFERROR(E5/C5-1,0) | I5: =IF(G5="No","Missing receipt",IF(ABS(H5)>0.05,"Over 5%: explain",IF(E5>F5,"Balance due","OK")))
A6: Partner dinner | B6: Harbour Catering | C6: 12000 | D6: 12000 | E6: 12900 | F6: 6000 | G6: Yes | H6: =IFERROR(E6/C6-1,0) | I6: =IF(G6="No","Missing receipt",IF(ABS(H6)>0.05,"Over 5%: explain",IF(E6>F6,"Balance due","OK")))
A7: Swag | B7: Swag Supply Co. | C7: 9000 | D7: 8600 | E7: 8600 | F7: 8600 | G7: Yes | H7: =IFERROR(E7/C7-1,0) | I7: =IF(G7="No","Missing receipt",IF(ABS(H7)>0.05,"Over 5%: explain",IF(E7>F7,"Balance due","OK")))
A8: Signage + badges | B8: Print Lab | C8: 4000 | D8: 0 | E8: 0 | F8: 0 | G8: No | H8: =IFERROR(E8/C8-1,0) | I8: =IF(G8="No","Missing receipt",IF(ABS(H8)>0.05,"Over 5%: explain",IF(E8>F8,"Balance due","OK")))
A9: Team travel | B9: Airlines + hotel | C9: 22000 | D9: 0 | E9: 20750 | F9: 20750 | G9: No | H9: =IFERROR(E9/C9-1,0) | I9: =IF(G9="No","Missing receipt",IF(ABS(H9)>0.05,"Over 5%: explain",IF(E9>F9,"Balance due","OK")))
A10: Shipping | B10: Freight | C10: 3500 | D10: 3500 | E10: 3900 | F10: 3900 | G10: Yes | H10: =IFERROR(E10/C10-1,0) | I10: =IF(G10="No","Missing receipt",IF(ABS(H10)>0.05,"Over 5%: explain",IF(E10>F10,"Balance due","OK")))
A11: Total | C11: =SUM(C5:C10) | D11: =SUM(D5:D10) | E11: =SUM(E5:E10) | F11: =SUM(F5:F10)

Sheet Travel
A1: Team travel
A2: One row per person. Keep confirmation numbers here, never in Slack.
A4: Name | B4: Role at event | C4: From | D4: Arrive | E4: Depart | F4: Flight booked | G4: Hotel booked | H4: Confirmation | I4: Dietary / access needs
A5: Team member A | B5: Booth lead | C5: YYZ | D5: Oct 25 | E5: Oct 28 | F5: Yes | G5: Yes | H5: Sample-0001
A6: Team member B | B6: Speaker support | C6: YVR | D6: Oct 25 | E6: Oct 28 | F6: Yes | G6: Yes | H6: Sample-0002 | I6: Vegetarian
A7: Team member C | B7: Partnerships | C7: YYC | D7: Oct 26 | E7: Oct 28 | F7: Yes | G7: No
A8: Team member D | B8: Volunteer lead | C8: YYZ | D8: Oct 24 | E8: Oct 28 | F8: No | G8: No

Sheet Shipping
A1: Shipping and swag
A2: Ship to the venue's advance warehouse inside its receiving window. Track every box.
A4: Item | B4: Qty | C4: Ship from | D4: Ship to | E4: Carrier | F4: Tracking # | G4: Ship by | H4: Delivered?
A5: Booth kit (3 cases) | B5: 3 | C5: Toronto office | D5: Venue advance warehouse | E5: Courier | F5: SAMPLE-TRK-01 | G5: Oct 12 | H5: In transit
A6: Swag: notebooks | B6: 1200 | C6: Supplier | D6: Venue advance warehouse | E6: Freight | F6: SAMPLE-TRK-02 | G6: Oct 9 | H6: Delivered
A7: Badge stock + lanyards | B7: 1 | C7: Print Lab | D7: Venue | E7: Courier | G7: Oct 19 | H7: Not shipped

Sheet Volunteers
A1: Volunteer roster
A2: Each shift has a lead, a briefing and a backup.
A4: Shift | B4: Station | C4: Time | D4: Volunteers needed | E4: Assigned | F4: Gap | G4: Lead
A5: Day 1 AM | B5: Registration desk | C5: 7:00-11:00 | D5: 6 | E5: 6 | F5: =D5-E5
A6: Day 1 AM | B6: Session room monitors | C6: 8:30-12:30 | D6: 8 | E6: 6 | F6: =D6-E6
A7: Day 1 PM | B7: Info desk | C7: 12:00-17:00 | D7: 3 | E7: 3 | F7: =D7-E7
A8: Day 2 AM | B8: Registration desk | C8: 7:30-10:30 | D8: 4 | E8: 2 | F8: =D8-E8
A9: Day 2 PM | B9: Expo hall guides | C9: 12:00-16:00 | D9: 4 | E9: 4 | F9: =D9-E9

Sheet Comms calendar
A1: Stakeholder comms calendar
A2: Every email has an owner, an audience and a send date tied to the event date.
A4: Audience | B4: Email | C4: Days before (+) / after (-) | D4: Send date | E4: Owner | F4: Status
A5: Speakers | B5: Logistics pack: arrival, green room, AV check | C5: 14 | D5: ='Logistics'!$C$3-C5 | E5: Coordinator | F5: Not started
A6: Sponsors | B6: Booth move-in times and asset deadline | C6: 14 | D6: ='Logistics'!$C$3-C6 | E6: Coordinator | F6: Not started
A7: Attendees | B7: Know before you go | C7: 7 | D7: ='Logistics'!$C$3-C7 | E7: Coordinator | F7: Not started
A8: Volunteers | B8: Shift confirmation + briefing deck | C8: 7 | D8: ='Logistics'!$C$3-C8 | E8: Coordinator | F8: Not started
A9: Speakers | B9: Final reminder + day-of contact | C9: 2 | D9: ='Logistics'!$C$3-C9 | E9: Coordinator | F9: Not started
A10: Attendees | B10: Day 1 morning: schedule + app | C10: 0 | D10: ='Logistics'!$C$3-C10 | E10: Coordinator | F10: Not started
A11: Attendees | B11: Thank you + recordings | C11: -2 | D11: ='Logistics'!$C$3-C11 | E11: Coordinator | F11: Not started
A12: Sponsors | B12: Leads + results recap | C12: -5 | D12: ='Logistics'!$C$3-C12 | E12: Coordinator | F12: Not started
A13: Volunteers | B13: Thank you + feedback form | C13: -3 | D13: ='Logistics'!$C$3-C13 | E13: Coordinator | F13: Not started

Sheet Partner onboarding
A1: Partner onboarding · first 30 days
A2: Same steps for every new partner, so nothing depends on memory.
A4: Day | B4: Step | C4: Owner | D4: Done?
A5: 1 | B5: Welcome email + kickoff call booked | C5: Coordinator | D5: No
A6: 2 | B6: Partner record created, contacts and logo collected | C6: Coordinator | D6: No
A7: 5 | B7: Kickoff call: goals, audience, first co-marketing idea | C7: Partner manager | D7: No
A8: 7 | B8: Partner kit sent: brand rules, messaging, co-branding do's and don'ts | C8: Coordinator | D8: No
A9: 14 | B9: Listing or landing page live | C9: Partner manager | D9: No
A10: 21 | B10: First joint activity scheduled (webinar, post or event) | C10: Partner manager | D10: No
A11: 30 | B11: 30-day check-in + first report | C11: Coordinator | D11: No

Sheet Status + risks
A1: Weekly status and risk log
A2: Green = on track, Amber = at risk, Red = blocked. Every risk has an owner and a next step.
A4: Workstream | B4: Status | C4: This week | D4: Next week | E4: Risk | F4: Owner | G4: Next step
A5: Logistics | B5: Green | C5: Booth kit shipped, travel booked | D5: Signage to print | F5: Coordinator
A6: Speakers | B6: Amber | C6: 32 of 40 slide decks in | D6: Chase final 8 | E6: Late slides delay AV prep | F6: Program manager | G6: Personal follow-up today, deadline Friday
A7: Sponsors | B7: Amber | C7: 2 sponsors missing logo files | D7: Assets locked | E7: Signage reprint cost | F7: Partnerships | G7: Call both sponsors
A8: Volunteers | B8: Red | C8: 4 shifts short | D8: Fill gaps, send briefing | E8: Registration line too long on Day 2 | F8: Coordinator | G8: Ask the team on Slack + backup list

Sheet AI workflow log
A1: AI workflow log
A2: Every AI-assisted process: what it does, who checks it, and the time it saves (estimate, measured after 4 weeks).
A4: Workflow | B4: Tools | C4: Input | D4: AI step | E4: Human review | F4: Minutes before | G4: Minutes after | H4: Saved per week (est.) | I4: Status
A5: Receipts to reconciliation | B5: Google Forms, Sheets, Gemini | C5: Receipt photos | D5: Read vendor, date, amount, category | E5: Coordinator checks every line vs card statement | F5: 90 | G5: 25 | H5: =F5-G5 | I5: Testing
A6: Speaker bios to session pages | B6: Google Forms, Sheets, Gemini | C6: Speaker form | D6: Trim bios to 60 words, match style guide | E6: Program manager approves each bio | F6: 120 | G6: 30 | H6: =F6-G6 | I6: Testing
A7: Shared inbox triage | B7: Gmail, Slack, Gemini | C7: New emails | D7: Label, priority, draft reply | E7: Coordinator edits and sends | F7: 150 | G7: 60 | H7: =F7-G7 | I7: Testing
A8: Post-event report | B8: Sheets, Slides, Gemini | C8: Survey + lead data | D8: Summarize results and themes | E8: Coordinator checks numbers vs source | F8: 240 | G8: 90 | H8: =F8-G8 | I8: Testing
G10: Total | H10: =SUM(H5:H8)
