Workbook

Sheet Read me
A1: Media plan workbook · sample
A2: Made by Durva Thakkar for the Klick Media Planning team · durvathakkar.com/klick
A4: What this is | B4: A working media plan for a sample brief: an unbranded migraine awareness campaign (US, patients + HCPs), 12 weeks, $1.2M.
A5: Important | B5: The brief is a sample I wrote. Rates and benchmarks are planning assumptions, not vendor quotes. Swap in real quotes and the whole workbook recalculates.
A6: How to use | B6: 1) Change the budget in 'Media plan'!C4 or any channel's share in column C. 2) Enter delivered spend in 'Pacing'. 3) Enter IO and invoice amounts in 'Reconciliation'.
A7: Tabs | B7: Media plan · Flowchart · Pacing · Reconciliation · Naming · Compliance QA
A8: Colour key | B8: Blue cells are inputs. Everything else is a formula.

Sheet Media plan
A1: Media plan · Unbranded migraine awareness (sample)
A2: US · Jan 4 to Mar 28, 2027 · 12 weeks
B4: Total budget | C4: 1200000
A6: Channel | B6: Audience | C6: Share of budget | D6: Budget | E6: Buy type | F6: Rate (assumption) | G6: Est. delivery | H6: Unit | I6: Primary KPI
A7: Paid search (Google, Microsoft) | B7: Patients searching symptoms | C7: 0.22 | D7: =$C$4*C7 | E7: CPC | F7: 3.5 | G7: =IFERROR(D7/F7,0) | H7: Clicks | I7: CTR, cost per qualified visit
A8: Programmatic display (DSP, contextual health) | B8: Patients, health content readers | C8: 0.18 | D8: =$C$4*C8 | E8: CPM | F8: 9 | G8: =IFERROR(D8/F8*1000,0) | H8: Impressions | I8: Viewability, CTR
A9: Online video + CTV | B9: Adults 25-54, broad + contextual | C9: 0.2 | D9: =$C$4*C9 | E9: CPM | F9: 28 | G9: =IFERROR(D9/F9*1000,0) | H9: Impressions | I9: Video completion rate
A10: Paid social (Meta, broad + contextual) | B10: Adults 25-54, no condition targeting | C10: 0.14 | D10: =$C$4*C10 | E10: CPM | F10: 11 | G10: =IFERROR(D10/F10*1000,0) | H10: Impressions | I10: Reach, frequency, CTR
A11: Mobile in-app | B11: Patients on health and lifestyle apps | C11: 0.06 | D11: =$C$4*C11 | E11: CPM | F11: 7 | G11: =IFERROR(D11/F11*1000,0) | H11: Impressions | I11: CTR, viewability
A12: HCP endemic (Medscape, Doximity) | B12: Neurologists, primary care (NPI verified) | C12: 0.12 | D12: =$C$4*C12 | E12: CPM | F12: 60 | G12: =IFERROR(D12/F12*1000,0) | H12: Impressions | I12: HCP reach, engagement
A13: HCP email (endemic lists) | B13: Neurologists, primary care (NPI verified) | C13: 0.05 | D13: =$C$4*C13 | E13: CPM | F13: 250 | G13: =IFERROR(D13/F13*1000,0) | H13: Sends | I13: Open rate, click rate
A14: Ad serving, verification, contingency | B14: All | C14: 0.03 | D14: =$C$4*C14 | E14: Flat | F14: 0 | G14: 0 | H14: n/a | I14: Brand safety, IVT rate
A15: Total | C15: =SUM(C7:C14) | D15: =SUM(D7:D14)
A16: Check | C16: =IF(ROUND(C15,4)=1,"OK: shares add to 100%","Fix: shares add to "&TEXT(C15,"0.0%"))

Sheet Flowchart
A1: Flowchart · weekly flighting
A2: 1 = live that week. Weekly budget = channel budget ÷ live weeks.
A4: Channel | B4: W1 Jan 4 | C4: W2 Jan 11 | D4: W3 Jan 18 | E4: W4 Jan 25 | F4: W5 Feb 1 | G4: W6 Feb 8 | H4: W7 Feb 15 | I4: W8 Feb 22 | J4: W9 Mar 1 | K4: W10 Mar 8 | L4: W11 Mar 15 | M4: W12 Mar 22 | N4: Live weeks | O4: Weekly budget
A5: Paid search (Google, Microsoft) | B5: 1 | C5: 1 | D5: 1 | E5: 1 | F5: 1 | G5: 1 | H5: 1 | I5: 1 | J5: 1 | K5: 1 | L5: 1 | M5: 1 | N5: =SUM(B5:M5) | O5: =IFERROR('Media plan'!D7/N5,0)
A6: Programmatic display (DSP, contextual health) | B6: 1 | C6: 1 | D6: 1 | E6: 1 | F6: 1 | G6: 1 | H6: 1 | I6: 1 | J6: 1 | K6: 1 | L6: 1 | M6: 1 | N6: =SUM(B6:M6) | O6: =IFERROR('Media plan'!D8/N6,0)
A7: Online video + CTV | B7: 1 | C7: 1 | D7: 1 | E7: 1 | F7: 0 | G7: 0 | H7: 1 | I7: 1 | J7: 1 | K7: 1 | L7: 0 | M7: 0 | N7: =SUM(B7:M7) | O7: =IFERROR('Media plan'!D9/N7,0)
A8: Paid social (Meta, broad + contextual) | B8: 1 | C8: 1 | D8: 1 | E8: 1 | F8: 1 | G8: 1 | H8: 1 | I8: 1 | J8: 1 | K8: 1 | L8: 1 | M8: 1 | N8: =SUM(B8:M8) | O8: =IFERROR('Media plan'!D10/N8,0)
A9: Mobile in-app | B9: 0 | C9: 0 | D9: 1 | E9: 1 | F9: 1 | G9: 1 | H9: 1 | I9: 1 | J9: 1 | K9: 1 | L9: 0 | M9: 0 | N9: =SUM(B9:M9) | O9: =IFERROR('Media plan'!D11/N9,0)
A10: HCP endemic (Medscape, Doximity) | B10: 1 | C10: 1 | D10: 1 | E10: 1 | F10: 1 | G10: 1 | H10: 1 | I10: 1 | J10: 1 | K10: 1 | L10: 1 | M10: 1 | N10: =SUM(B10:M10) | O10: =IFERROR('Media plan'!D12/N10,0)
A11: HCP email (endemic lists) | B11: 0 | C11: 1 | D11: 0 | E11: 0 | F11: 1 | G11: 0 | H11: 0 | I11: 1 | J11: 0 | K11: 0 | L11: 1 | M11: 0 | N11: =SUM(B11:M11) | O11: =IFERROR('Media plan'!D13/N11,0)
A12: Ad serving, verification, contingency | B12: 1 | C12: 1 | D12: 1 | E12: 1 | F12: 1 | G12: 1 | H12: 1 | I12: 1 | J12: 1 | K12: 1 | L12: 1 | M12: 1 | N12: =SUM(B12:M12) | O12: =IFERROR('Media plan'!D14/N12,0)

Sheet Pacing
A1: Pacing · are we spending on plan?
A2: Pace = delivered spend ÷ (budget × share of flight elapsed). 90% to 110% is on pace.
B4: Flight days | C4: 84
B5: Days elapsed | C5: 42
B6: Share elapsed | C6: =C5/C4
A8: Channel | B8: Budget | C8: Expected to date | D8: Delivered to date | E8: Pace | F8: Status | G8: Note
A9: Paid search (Google, Microsoft) | B9: ='Media plan'!D7 | C9: =B9*$C$6 | D9: =ROUND(B9*0.49,0) | E9: =IFERROR(D9/C9,0) | F9: =IF(E9>1.1,"Over: slow down",IF(E9<0.9,"Under: push or reallocate","On pace"))
A10: Programmatic display (DSP, contextual health) | B10: ='Media plan'!D8 | C10: =B10*$C$6 | D10: =ROUND(B10*0.41,0) | E10: =IFERROR(D10/C10,0) | F10: =IF(E10>1.1,"Over: slow down",IF(E10<0.9,"Under: push or reallocate","On pace"))
A11: Online video + CTV | B11: ='Media plan'!D9 | C11: =B11*$C$6 | D11: =ROUND(B11*0.55,0) | E11: =IFERROR(D11/C11,0) | F11: =IF(E11>1.1,"Over: slow down",IF(E11<0.9,"Under: push or reallocate","On pace"))
A12: Paid social (Meta, broad + contextual) | B12: ='Media plan'!D10 | C12: =B12*$C$6 | D12: =ROUND(B12*0.5,0) | E12: =IFERROR(D12/C12,0) | F12: =IF(E12>1.1,"Over: slow down",IF(E12<0.9,"Under: push or reallocate","On pace"))
A13: Mobile in-app | B13: ='Media plan'!D11 | C13: =B13*$C$6 | D13: =ROUND(B13*0.3,0) | E13: =IFERROR(D13/C13,0) | F13: =IF(E13>1.1,"Over: slow down",IF(E13<0.9,"Under: push or reallocate","On pace"))
A14: HCP endemic (Medscape, Doximity) | B14: ='Media plan'!D12 | C14: =B14*$C$6 | D14: =ROUND(B14*0.47,0) | E14: =IFERROR(D14/C14,0) | F14: =IF(E14>1.1,"Over: slow down",IF(E14<0.9,"Under: push or reallocate","On pace"))
A15: HCP email (endemic lists) | B15: ='Media plan'!D13 | C15: =B15*$C$6 | D15: =ROUND(B15*0.33,0) | E15: =IFERROR(D15/C15,0) | F15: =IF(E15>1.1,"Over: slow down",IF(E15<0.9,"Under: push or reallocate","On pace"))
A16: Ad serving, verification, contingency | B16: ='Media plan'!D14 | C16: =B16*$C$6 | D16: =ROUND(B16*0.5,0) | E16: =IFERROR(D16/C16,0) | F16: =IF(E16>1.1,"Over: slow down",IF(E16<0.9,"Under: push or reallocate","On pace"))

Sheet Reconciliation
A1: Reconciliation · plan vs IO vs delivered vs invoiced
A2: Flag anything over 2% so billing questions are raised before month end.
A4: Vendor / channel | B4: Planned | C4: IO signed | D4: Delivered (ad server) | E4: Invoiced | F4: Invoice vs delivered | G4: Variance % | H4: Action
A5: Paid search (Google, Microsoft) | B5: ='Media plan'!D7 | C5: =ROUND(B5*1,0) | D5: =ROUND(B5*1,0) | E5: =ROUND(B5*1,0) | F5: =E5-D5 | G5: =IFERROR(F5/D5,0) | H5: =IF(ABS(G5)>0.02,"Query vendor before approving","OK to approve")
A6: Programmatic display (DSP, contextual health) | B6: ='Media plan'!D8 | C6: =ROUND(B6*1,0) | D6: =ROUND(B6*0.97,0) | E6: =ROUND(B6*0.97,0) | F6: =E6-D6 | G6: =IFERROR(F6/D6,0) | H6: =IF(ABS(G6)>0.02,"Query vendor before approving","OK to approve")
A7: Online video + CTV | B7: ='Media plan'!D9 | C7: =ROUND(B7*0.98,0) | D7: =ROUND(B7*0.99,0) | E7: =ROUND(B7*1.02,0) | F7: =E7-D7 | G7: =IFERROR(F7/D7,0) | H7: =IF(ABS(G7)>0.02,"Query vendor before approving","OK to approve")
A8: Paid social (Meta, broad + contextual) | B8: ='Media plan'!D10 | C8: =ROUND(B8*1,0) | D8: =ROUND(B8*1.0,0) | E8: =ROUND(B8*1.0,0) | F8: =E8-D8 | G8: =IFERROR(F8/D8,0) | H8: =IF(ABS(G8)>0.02,"Query vendor before approving","OK to approve")
A9: Mobile in-app | B9: ='Media plan'!D11 | C9: =ROUND(B9*1,0) | D9: =ROUND(B9*0.95,0) | E9: =ROUND(B9*0.95,0) | F9: =E9-D9 | G9: =IFERROR(F9/D9,0) | H9: =IF(ABS(G9)>0.02,"Query vendor before approving","OK to approve")
A10: HCP endemic (Medscape, Doximity) | B10: ='Media plan'!D12 | C10: =ROUND(B10*1,0) | D10: =ROUND(B10*1.0,0) | E10: =ROUND(B10*1.04,0) | F10: =E10-D10 | G10: =IFERROR(F10/D10,0) | H10: =IF(ABS(G10)>0.02,"Query vendor before approving","OK to approve")
A11: HCP email (endemic lists) | B11: ='Media plan'!D13 | C11: =ROUND(B11*1,0) | D11: =ROUND(B11*1.0,0) | E11: =ROUND(B11*1.0,0) | F11: =E11-D11 | G11: =IFERROR(F11/D11,0) | H11: =IF(ABS(G11)>0.02,"Query vendor before approving","OK to approve")
A12: Ad serving, verification, contingency | B12: ='Media plan'!D14 | C12: =ROUND(B12*1,0) | D12: =ROUND(B12*0.9,0) | E12: =ROUND(B12*0.9,0) | F12: =E12-D12 | G12: =IFERROR(F12/D12,0) | H12: =IF(ABS(G12)>0.02,"Query vendor before approving","OK to approve")

Sheet Naming
A1: Naming convention · campaigns, placements, creative, UTMs
A2: One name everywhere: plan, DSP, ad server, analytics. Underscores between parts, hyphens inside a part, no spaces.
A4: Client | B4: Brand | C4: Campaign | D4: Audience | E4: Channel | F4: Tactic | G4: Geo | H4: Start (YYYYMM) | I4: MLR code | J4: Generated name | K4: utm_campaign
A5: KLK | B5: UNB-MIGRAINE | C5: KNOW-YOUR-MIGRAINE | D5: PT | E5: SEARCH | F5: SYMPTOM-KW | G5: US | H5: 202701 | I5: MLR-0142 | J5: =UPPER(A5&"_"&B5&"_"&C5&"_"&D5&"_"&E5&"_"&F5&"_"&G5&"_"&H5&"_"&I5) | K5: =LOWER(B5&"_"&C5&"_"&H5)
A6: KLK | B6: UNB-MIGRAINE | C6: KNOW-YOUR-MIGRAINE | D6: PT | E6: CTV | F6: CONTEXT-HEALTH | G6: US | H6: 202701 | I6: MLR-0143 | J6: =UPPER(A6&"_"&B6&"_"&C6&"_"&D6&"_"&E6&"_"&F6&"_"&G6&"_"&H6&"_"&I6) | K6: =LOWER(B6&"_"&C6&"_"&H6)
A7: KLK | B7: UNB-MIGRAINE | C7: KNOW-YOUR-MIGRAINE | D7: HCP | E7: ENDEMIC | F7: NEURO-PCP | G7: US | H7: 202701 | I7: MLR-0150 | J7: =UPPER(A7&"_"&B7&"_"&C7&"_"&D7&"_"&E7&"_"&F7&"_"&G7&"_"&H7&"_"&I7) | K7: =LOWER(B7&"_"&C7&"_"&H7)
A10: Audience codes: PT = patient, HCP = healthcare professional, CG = caregiver.

Sheet Compliance QA
A1: Pre-launch QA · health media
A2: Tick every line before a placement goes live. Your MLR and legal teams have the final word; this is a coordinator's checklist.
A4: # | B4: Check | C4: Applies to | D4: Done?
A5: 1 | B5: Every creative has an approved MLR (medical, legal, regulatory) code, and the code is in the creative name | C5: All | D5: No
A6: 2 | B6: Branded Rx (US): fair balance and Important Safety Information are present and readable on every unit | C6: Branded | D6: No
A7: 3 | B7: Unbranded: no product name, colours or claims that could tie the ad to a product | C7: Unbranded | D7: No
A8: 4 | B8: Canada: Rx ads to consumers stay within name, price and quantity; HCP materials have PAAB clearance where needed | C8: Canada | D8: No
A9: 5 | B9: Google: account and ads follow the Healthcare and medicines policy; Rx ads in the US need Google certification | C9: Search | D9: No
A10: 6 | B10: Meta: no targeting or copy that implies someone has a health condition; check current limits on health data and events | C10: Social | D10: No
A11: 7 | B11: No retargeting from condition pages without consent; check state health-privacy laws such as Washington's My Health My Data Act | C11: All digital | D11: No
A12: 8 | B12: Patient site pixels and tags reviewed with privacy/legal (no health data sent to ad platforms) | C12: All digital | D12: No
A13: 9 | B13: HCP audiences are NPI-verified on endemic platforms | C13: HCP | D13: No
A14: 10 | B14: Brand safety, contextual exclusions and frequency caps set in every platform | C14: All | D14: No
A15: 11 | B15: Tracking: names and UTMs follow the Naming tab; links tested end to end | C15: All | D15: No
A16: 12 | B16: Trafficking sheet matches the plan: dates, budgets, sizes, landing pages | C16: All | D16: No
